{
  "track": {
    "name": "Alone, Pt. II",
    "mbid": "328ec0a4-820f-40ba-a67d-4138f244daa9",
    "url": "https://www.last.fm/music/Alan+Walker/_/Alone,+Pt.+II",
    "duration": "179000",
    "streamable": {
      "#text": "0",
      "fulltrack": "0"
    },
    "listeners": "237923",
    "playcount": "2102456",
    "artist": {
      "name": "Alan Walker",
      "mbid": "71d524e4-2ae2-4a3e-baa0-0c021925db7a",
      "url": "https://www.last.fm/music/Alan+Walker"
    },
    "album": {
      "artist": "Various Artists",
      "title": "538 Hitzone 93",
      "url": "https://www.last.fm/music/Various+Artists/538+Hitzone+93",
      "image": [
        {
          "#text": "https://lastfm.freetls.fastly.net/i/u/34s/cc564c5e80c49c78f16ef6caa99493c8.png",
          "size": "small"
        },
        {
          "#text": "https://lastfm.freetls.fastly.net/i/u/64s/cc564c5e80c49c78f16ef6caa99493c8.png",
          "size": "medium"
        },
        {
          "#text": "https://lastfm.freetls.fastly.net/i/u/174s/cc564c5e80c49c78f16ef6caa99493c8.png",
          "size": "large"
        },
        {
          "#text": "https://lastfm.freetls.fastly.net/i/u/300x300/cc564c5e80c49c78f16ef6caa99493c8.png",
          "size": "extralarge"
        }
      ]
    },
    "toptags": {
      "tag": []
    },
    "wiki": {
      "published": "22 Jul 2023, 19:15",
      "summary": "\"Alone, Pt. II\" is a song by British-Norwegian record producer and DJ Alan Walker and American singer Ava Max, released by Sony Music on 27 December 2019. It is a sequel to Walker's single \"Alone\" (2016). Many remixes of the song were published, among which those by Rave Republic, Toby Romeo, RetroVision, Da Tweekaz, and one by Alex Skrindo, in collaboration with Sebastian Wibe. Much like the original, \"Alone, Pt. II\" also garnered critical acclaim. The song reached the top 10 in Belgium, The Czech Republic, Norway, Poland, and Romania. <a href=\"http://www.last.fm/music/Alan+Walker/_/Alone,+Pt.+II\">Read more on Last.fm</a>.",
      "content": "\"Alone, Pt. II\" is a song by British-Norwegian record producer and DJ Alan Walker and American singer Ava Max, released by Sony Music on 27 December 2019. It is a sequel to Walker's single \"Alone\" (2016). Many remixes of the song were published, among which those by Rave Republic, Toby Romeo, RetroVision, Da Tweekaz, and one by Alex Skrindo, in collaboration with Sebastian Wibe. Much like the original, \"Alone, Pt. II\" also garnered critical acclaim. The song reached the top 10 in Belgium, The Czech Republic, Norway, Poland, and Romania. <a href=\"http://www.last.fm/music/Alan+Walker/_/Alone,+Pt.+II\">Read more on Last.fm</a>. User-contributed text is available under the Creative Commons By-SA License; additional terms may apply."
    }
  }
}