{
  "track": {
    "name": "My Head & My Heart",
    "mbid": "3a86f3ed-1ff0-4948-b65b-37c9b8cf7d6b",
    "url": "https://www.last.fm/music/Ava+Max/_/My+Head+&+My+Heart",
    "duration": "174000",
    "streamable": {
      "#text": "0",
      "fulltrack": "0"
    },
    "listeners": "297280",
    "playcount": "2891115",
    "artist": {
      "name": "Ava Max",
      "mbid": "add5f522-25df-41c4-815e-0ca9f60b83e4",
      "url": "https://www.last.fm/music/Ava+Max"
    },
    "album": {
      "artist": "Ava Max",
      "title": "My Head & My Heart (Acoustic)",
      "url": "https://www.last.fm/music/Ava+Max/My+Head+&+My+Heart+(Acoustic)",
      "image": [
        {
          "#text": "https://lastfm.freetls.fastly.net/i/u/34s/8c0a9e3e1cd7bf68aa9a74269a49cfe5.png",
          "size": "small"
        },
        {
          "#text": "https://lastfm.freetls.fastly.net/i/u/64s/8c0a9e3e1cd7bf68aa9a74269a49cfe5.png",
          "size": "medium"
        },
        {
          "#text": "https://lastfm.freetls.fastly.net/i/u/174s/8c0a9e3e1cd7bf68aa9a74269a49cfe5.png",
          "size": "large"
        },
        {
          "#text": "https://lastfm.freetls.fastly.net/i/u/300x300/8c0a9e3e1cd7bf68aa9a74269a49cfe5.png",
          "size": "extralarge"
        }
      ]
    },
    "toptags": {
      "tag": []
    },
    "wiki": {
      "published": "16 Mar 2021, 03:37",
      "summary": "\"My Head & My Heart\" is the eighth single from Ava Max’s debut studio album, Heaven & Hell. The song was digitally released 19 November 2020 through Atlantic Records. It is a dance-pop anthem that interpolates the 2000s song \"Around the World (La La La La La)\" by ATC, which is a cover of the 1998 composition \"Pesenka\" by Ruki Vverh!.\n\nIt was included on the digital reissue of Max's debut studio album Heaven & Hell (2020). The pop and dance song was written by Max <a href=\"http://www.last.fm/music/Ava+Max/_/My+Head+&+My+Heart\">Read more on Last.fm</a>.",
      "content": "\"My Head & My Heart\" is the eighth single from Ava Max’s debut studio album, Heaven & Hell. The song was digitally released 19 November 2020 through Atlantic Records. It is a dance-pop anthem that interpolates the 2000s song \"Around the World (La La La La La)\" by ATC, which is a cover of the 1998 composition \"Pesenka\" by Ruki Vverh!.\n\nIt was included on the digital reissue of Max's debut studio album Heaven & Hell (2020). The pop and dance song was written by Max, Madison Love, Aleksey Potekhin, Sergey Zhukov, Tia Scola, Earwulf, and Cirkut, with production handled by the latter two producers and Jonas Blue. The track was sent to US Contemporary Hit Radio on January 26, 2021.\n\n\"My Head & My Heart\" was an international commercial success, reaching #1 in Croatia, Germany, and Hungary and charting within the top 10 in over 10 other countries. The track was featured on numerous year end charts across the world, notably featured on Hungary's list for three years straight (2020, 2021, 2022). In the US, it peaked at #45 on the US Billboard Hot 100 and is certified Platinum. <a href=\"http://www.last.fm/music/Ava+Max/_/My+Head+&+My+Heart\">Read more on Last.fm</a>. User-contributed text is available under the Creative Commons By-SA License; additional terms may apply."
    }
  }
}