{
  "track": {
    "name": "You Broke My Heart",
    "mbid": "fefe480c-87ad-4441-9b89-3e3276b9a9a8",
    "url": "https://www.last.fm/music/Drake/_/You+Broke+My+Heart",
    "duration": "230000",
    "streamable": {
      "#text": "0",
      "fulltrack": "0"
    },
    "listeners": "346623",
    "playcount": "4216519",
    "artist": {
      "name": "Drake",
      "mbid": "9fff2f8a-21e6-47de-a2b8-7f449929d43f",
      "url": "https://www.last.fm/music/Drake"
    },
    "album": {
      "artist": "Drake",
      "title": "For All the Dogs Scary Hours Edition",
      "url": "https://www.last.fm/music/Drake/For+All+the+Dogs+Scary+Hours+Edition",
      "image": [
        {
          "#text": "https://lastfm.freetls.fastly.net/i/u/34s/3fe94ce0c96db8976248fd034b81f238.png",
          "size": "small"
        },
        {
          "#text": "https://lastfm.freetls.fastly.net/i/u/64s/3fe94ce0c96db8976248fd034b81f238.png",
          "size": "medium"
        },
        {
          "#text": "https://lastfm.freetls.fastly.net/i/u/174s/3fe94ce0c96db8976248fd034b81f238.png",
          "size": "large"
        },
        {
          "#text": "https://lastfm.freetls.fastly.net/i/u/300x300/3fe94ce0c96db8976248fd034b81f238.png",
          "size": "extralarge"
        }
      ]
    },
    "toptags": {
      "tag": [
        {
          "name": "2023",
          "url": "https://www.last.fm/tag/2023"
        },
        {
          "name": "Drake",
          "url": "https://www.last.fm/tag/Drake"
        },
        {
          "name": "Hip-Hop",
          "url": "https://www.last.fm/tag/Hip-Hop"
        },
        {
          "name": "rap",
          "url": "https://www.last.fm/tag/rap"
        },
        {
          "name": "pop rap",
          "url": "https://www.last.fm/tag/pop+rap"
        }
      ]
    },
    "wiki": {
      "published": "19 Nov 2023, 03:20",
      "summary": "“You Broke My Heart” is the sixth and final song in the deluxe edition of For All The Dogs, “For All The Dogs Scary Hours Edition”. The music video for this song released on December 20, 2023 <a href=\"http://www.last.fm/music/Drake/_/You+Broke+My+Heart\">Read more on Last.fm</a>.",
      "content": "“You Broke My Heart” is the sixth and final song in the deluxe edition of For All The Dogs, “For All The Dogs Scary Hours Edition”. The music video for this song released on December 20, 2023 <a href=\"http://www.last.fm/music/Drake/_/You+Broke+My+Heart\">Read more on Last.fm</a>. User-contributed text is available under the Creative Commons By-SA License; additional terms may apply."
    }
  }
}