{
  "track": {
    "name": "Break My Heart",
    "mbid": "ba2a214d-39b0-4b53-8b20-b2b80cf9bfab",
    "url": "https://www.last.fm/music/Dua+Lipa/_/Break+My+Heart",
    "duration": "221000",
    "streamable": {
      "#text": "0",
      "fulltrack": "0"
    },
    "listeners": "1061960",
    "playcount": "14347383",
    "artist": {
      "name": "Dua Lipa",
      "mbid": "6f1a58bf-9b1b-49cf-a44a-6cefad7ae04f",
      "url": "https://www.last.fm/music/Dua+Lipa"
    },
    "album": {
      "artist": "Various Artists",
      "title": "Just Hits",
      "url": "https://www.last.fm/music/Various+Artists/Just+Hits",
      "image": [
        {
          "#text": "https://lastfm.freetls.fastly.net/i/u/34s/e9d4da5f4e041df86db634f0d0aa5b67.png",
          "size": "small"
        },
        {
          "#text": "https://lastfm.freetls.fastly.net/i/u/64s/e9d4da5f4e041df86db634f0d0aa5b67.png",
          "size": "medium"
        },
        {
          "#text": "https://lastfm.freetls.fastly.net/i/u/174s/e9d4da5f4e041df86db634f0d0aa5b67.png",
          "size": "large"
        },
        {
          "#text": "https://lastfm.freetls.fastly.net/i/u/300x300/e9d4da5f4e041df86db634f0d0aa5b67.png",
          "size": "extralarge"
        }
      ]
    },
    "toptags": {
      "tag": [
        {
          "name": "pop",
          "url": "https://www.last.fm/tag/pop"
        },
        {
          "name": "Disco",
          "url": "https://www.last.fm/tag/Disco"
        },
        {
          "name": "dance-pop",
          "url": "https://www.last.fm/tag/dance-pop"
        },
        {
          "name": "dance",
          "url": "https://www.last.fm/tag/dance"
        },
        {
          "name": "nu-disco",
          "url": "https://www.last.fm/tag/nu-disco"
        }
      ]
    },
    "wiki": {
      "published": "05 Feb 2020, 08:03",
      "summary": "\"Break My Heart\" is a song by English singer Dua Lipa, released on March 25, 2020 through Warner Records as the third single from her second studio album \"Future Nostalgia\". The song was written by Lipa, Alexandra Tamposi, Blair Gormal and its producers The Monsters and the Strangerz. \"Break My Heart\" samples the melody from \"Need You Tonight\" by INXS, thus Michael Hutchence and Andrew Farriss are also credited as songwriters.\n\n\"Break My Heart\" was leaked in January 2020 along with \"Physical\" and \"If It Ain't Me\" <a href=\"http://www.last.fm/music/Dua+Lipa/_/Break+My+Heart\">Read more on Last.fm</a>.",
      "content": "\"Break My Heart\" is a song by English singer Dua Lipa, released on March 25, 2020 through Warner Records as the third single from her second studio album \"Future Nostalgia\". The song was written by Lipa, Alexandra Tamposi, Blair Gormal and its producers The Monsters and the Strangerz. \"Break My Heart\" samples the melody from \"Need You Tonight\" by INXS, thus Michael Hutchence and Andrew Farriss are also credited as songwriters.\n\n\"Break My Heart\" was leaked in January 2020 along with \"Physical\" and \"If It Ain't Me\", an unreleased collaboration with Normani. Lipa first revealed that the song would serve as the third single from Future Nostalgia in March 2020 on the Australian TV show Sunrise. Lipa revealed the cover art and announced that the song would be released on March 27, 2020. She later pushed up the release of the song to March 25, 2020 due to \"Future Nostalgia\" being released. <a href=\"http://www.last.fm/music/Dua+Lipa/_/Break+My+Heart\">Read more on Last.fm</a>. User-contributed text is available under the Creative Commons By-SA License; additional terms may apply."
    }
  }
}